pydebug/__init__.py
pydebug/base.py
pydebug/dis.py
pydebug/info.py
pydebug/pdb.py
pydebug/profiler.py
python_pydebug-0.2.dist-info/LICENSE
python_pydebug-0.2.dist-info/METADATA
python_pydebug-0.2.dist-info/WHEEL
python_pydebug-0.2.dist-info/top_level.txt
python_pydebug-0.2.dist-info/RECORD
