Metadata-Version: 2.1
Name: python-pydebug
Version: 0.2
Summary: A set of debugging decorators
Home-page: http://github.com/benmezger/pydebug
Author: Ben Mezger
Author-email: me@benmezger.nl
License: MIT
Platform: UNKNOWN
